README.txt
setup.py
pulsebuildmonitor/__init__.py
pulsebuildmonitor/daemon.py
pulsebuildmonitor/factory.py
pulsebuildmonitor/pulsebuildmonitor.py
pulsebuildmonitor.egg-info/PKG-INFO
pulsebuildmonitor.egg-info/SOURCES.txt
pulsebuildmonitor.egg-info/dependency_links.txt
pulsebuildmonitor.egg-info/not-zip-safe
pulsebuildmonitor.egg-info/requires.txt
pulsebuildmonitor.egg-info/top_level.txt