Metadata-Version: 1.0
Name: pulsebuildmonitor
Version: 0.62
Summary: montior mozilla tinderbox builds via pulse
Home-page: http://hg.mozilla.org/automation/pulsebuildmonitor
Author: Jonathan Griffin
Author-email: jgriffin@mozilla.com
License: MPL
Platform: UNKNOWN
